bang/__init__.py
bang/core/__init__.py
bang/core/attractors/blocks/attractors_paralel.py
bang/core/attractors/blocks/block_attractors.py
bang/core/attractors/blocks/crossing.py
bang/core/attractors/blocks/divide_and_conquer.py
bang/core/attractors/blocks/graph.py
bang/core/attractors/blocks/node_selection.py
bang/core/attractors/monolithic/monolithic.py
bang/core/attractors/monolithic/segmentation.py
bang/core/attractors/monte_carlo/count_states.py
bang/core/attractors/monte_carlo/merge_attractors.py
bang/core/attractors/monte_carlo/monte_carlo.py
bang/core/pbn/array_management.py
bang/core/pbn/pbn.py
bang/core/pbn/simple_steps.py
bang/core/pbn/truthtable_reduction.py
bang/core/pbn/utils/integer_functions.py
bang/core/pbn/utils/state_printing.py
bang/core/simulation/__init__.py
bang/core/simulation/common.py
bang/core/simulation/cpu/__init__.py
bang/core/simulation/cpu/perturbation.py
bang/core/simulation/cpu/state_management.py
bang/core/simulation/cpu/functions/async_one_random.py
bang/core/simulation/cpu/functions/async_random_order.py
bang/core/simulation/cpu/functions/synchronous.py
bang/core/simulation/cuda/__init__.py
bang/core/simulation/cuda/perturbation.py
bang/core/simulation/cuda/state_management.py
bang/core/simulation/cuda/kernels/async_one_random.py
bang/core/simulation/cuda/kernels/async_random_order.py
bang/core/simulation/cuda/kernels/synchronous.py
bang/parsing/__init__.py
bang/parsing/assa.py
bang/parsing/bool_func.py
bang/parsing/sbml.py
bang/visualization/__init__.py
bang/visualization/blocks.py
bang/visualization/dependency.py
bang/visualization/trajectory.py
bang_gpu-0.4.0.dist-info/licenses/LICENSE
bang_gpu-0.4.0.dist-info/METADATA
bang_gpu-0.4.0.dist-info/WHEEL
bang_gpu-0.4.0.dist-info/top_level.txt
bang_gpu-0.4.0.dist-info/RECORD
