Metadata-Version: 2.4
Name: bang-gpu
Version: 0.4.0
Author-email: Mikołaj Czarnecki <mc448206@students.mimuw.edu.pl>, Jan Jagodziński <jan.jagodzinski@gmail.com>, Bartłomiej Parapura <b.parapura@student.uw.edu.pl>, Paweł Zając <pawel.andrzej.zajac@gmail.com>
License:                                  Apache License
Project-URL: Homepage, https://github.com/zpp20/bang
Project-URL: Repository, https://github.com/zpp20/bang
Project-URL: Changelog, https://github.com/zpp20/bang/blob/main/CHANGELOG.md
Classifier: Programming Language :: Python :: 3
Classifier: Programming Language :: Python :: 3.10
Classifier: Programming Language :: Python :: 3.11
Classifier: Programming Language :: Python :: 3.12
Requires-Python: >=3.10
License-File: LICENSE
Requires-Dist: python-libsbml==5.20.4
Requires-Dist: numba-cuda==0.4.0
Requires-Dist: numba==0.61.0
Requires-Dist: numpy==2.0.2
Requires-Dist: graphviz==0.20.3
Provides-Extra: dev
Requires-Dist: ruff; extra == "dev"
Requires-Dist: pyright<2.0,>=1.1; extra == "dev"
Requires-Dist: black<24.0,>=23.0; extra == "dev"
Requires-Dist: isort<5.13,>=5.12; extra == "dev"
Requires-Dist: pytest; extra == "dev"
Requires-Dist: pytest-sphinx; extra == "dev"
Requires-Dist: pytest-cov; extra == "dev"
Requires-Dist: twine>=1.11.0; extra == "dev"
Requires-Dist: build; extra == "dev"
Requires-Dist: setuptools; extra == "dev"
Requires-Dist: wheel; extra == "dev"
Requires-Dist: Sphinx<7.1.0,>=4.3.0; extra == "dev"
Requires-Dist: furo==2023.7.26; extra == "dev"
Requires-Dist: myst-parser<2.1,>=1.0; extra == "dev"
Requires-Dist: sphinx-copybutton==0.5.2; extra == "dev"
Requires-Dist: sphinx-autobuild==2021.3.14; extra == "dev"
Requires-Dist: sphinx-autodoc-typehints==1.23.3; extra == "dev"
Requires-Dist: packaging; extra == "dev"
Dynamic: license-file
